breakout/__index__.py
breakout-0.1.0.dist-info/LICENSE
breakout-0.1.0.dist-info/WHEEL
breakout-0.1.0.dist-info/METADATA
breakout-0.1.0.dist-info/RECORD
