Metadata-Version: 2.1
Name: breakout
Version: 0.1.0
Summary: Remote breakpoint.
Home-page: https://github.com/supakeen/breakout
License: MIT
Keywords: remote,debugging,breakpoint
Author: supakeen
Author-email: cmdr@supakeen.com
Requires-Python: >=3.6,<4
Classifier: License :: OSI Approved :: MIT License
Classifier: Programming Language :: Python
Classifier: Programming Language :: Python :: 3
Classifier: Programming Language :: Python :: 3.6
Classifier: Programming Language :: Python :: 3.7
Classifier: Programming Language :: Python :: 3.8
Project-URL: Repository, https://github.com/supakeen/breakout
